{
    "projects": [
        {
            "link": {
                "href": "./cafeteria/",
                "title": "Cafeteria"
            },
            "cover": {
                "src": "./assets/imgs/project-covers/cafeteria-cover.webp",
                "alt": "Eringer Kaffee"
            }
        },
        {
            "link": {
                "href": "./alpar-table/",
                "title": "Site de empresa em tabela"
            },
            "cover": {
                "src": "./assets/imgs/project-covers/alpar_table-cover.webp",
                "alt": "Alpar Table"
            }
        },
        {
            "link": {
                "href": "./alpar/",
                "title": "Site de empresa"
            },
            "cover": {
                "src": "./assets/imgs/project-covers/alpar-cover.webp",
                "alt": "Alpar"
            }
        },
        {
            "link": {
                "href": "./crosstech-podcast/",
                "title": "Podcast"
            },
            "cover": {
                "src": "./assets/imgs/project-covers/podcast-cover.webp",
                "alt": "Cross Tech"
            }
        },
        {
            "link": {
                "href": "./blog/",
                "title": "Blog"
            },
            "cover": {
                "src": "./assets/imgs/project-covers/blog-cover.webp",
                "alt": "Alpar Rocket Blog"
            }
        },
        {
            "link": {
                "href": "./card/",
                "title": "Card"
            },
            "cover": {
                "src": "./assets/imgs/project-covers/card-cover.webp",
                "alt": "Cartão de Perfil"
            }
        },
        {
            "link": {
                "href": "./baralho/",
                "title": "Baralho"
            },
            "cover": {
                "src": "./assets/imgs/project-covers/baralho-cover.webp",
                "alt": "Carta de Baralho"
            }
        },
        {
            "link": {
                "href": "./previsao/",
                "title": "Previsão do Clima"
            },
            "cover": {
                "src": "./assets/imgs/project-covers/previsao-cover.webp",
                "alt": "Previsão do Clima"
            }
        },
        {
            "link": {
                "href": "./portfolio-bootstrap/",
                "title": "Portfólio em Bootstrap"
            },
            "cover": {
                "src": "./assets/imgs/project-covers/portfolio_bootstrap-cover.webp",
                "alt": "Portfólio em Bootstrap"
            }
        },
        {
            "link": {
                "href": "./portfolio-bootstrap/gedotech/",
                "title": "Site em Bootstrap"
            },
            "cover": {
                "src": "./assets/imgs/project-covers/gedotech_bootstrap-cover.webp",
                "alt": "gedotech em Bootstrap"
            }
        },
        {
            "link": {
                "href": "./sistema-escolar/",
                "title": "Sistema Escolar"
            },
            "cover": {
                "src": "./assets/imgs/project-covers/sistema_escolar-cover.webp",
                "alt": "Sistema Escolar"
            }
        },
        {
            "link": {
                "href": "./automacao-luzes/",
                "title": "Automação de Luzes"
            },
            "cover": {
                "src": "./assets/imgs/project-covers/automacao_luzes-cover.webp",
                "alt": "Automação de Luzes"
            }
        },
        {
            "link": {
                "href": "./gerenciamento-usuarios-escola/",
                "title": "Gerenciamento de Usuários de uma Escola"
            },
            "cover": {
                "src": "./assets/imgs/project-covers/gerenciamento_usuarios_escola-cover.webp",
                "alt": "Gerenciamento de Usuarios de uma Escola em AngularJS"
            }
        },
        {
            "link": {
                "href": "./lista-tarefas/",
                "title": "Lista de Tarefas"
            },
            "cover": {
                "src": "./assets/imgs/project-covers/lista_tarefas-cover.webp",
                "alt": "Lista de Tarefas em AngularJS"
            }
        },
        {
            "link": {
                "href": "./previsao-angular/",
                "title": "Previsão do Clima em AngularJS"
            },
            "cover": {
                "src": "./assets/imgs/project-covers/previsao_angular-cover.webp",
                "alt": "Previsão do Clima em AngularJS"
            }
        },
        {
            "link": {
                "href": "https://github.com/SenaNilo/DesafioFullStack-LojaVirtual",
                "title": "Loja Virtual"
            },
            "cover": {
                "src": "./assets/imgs/project-covers/loja_virtual-cover.webp",
                "alt": "Loja Virtual"
            }
        }
    ]
}